MANIFEST.in
README.txt
setup.cfg
setup.py
vs.jquerybookmarks-configure.zcml
docs/HISTORY.txt
docs/INSTALL.txt
docs/LICENSE.GPL
docs/LICENSE.txt
vs/__init__.py
vs.jquerybookmarks.egg-info/PKG-INFO
vs.jquerybookmarks.egg-info/SOURCES.txt
vs.jquerybookmarks.egg-info/dependency_links.txt
vs.jquerybookmarks.egg-info/entry_points.txt
vs.jquerybookmarks.egg-info/namespace_packages.txt
vs.jquerybookmarks.egg-info/not-zip-safe
vs.jquerybookmarks.egg-info/paster_plugins.txt
vs.jquerybookmarks.egg-info/requires.txt
vs.jquerybookmarks.egg-info/top_level.txt
vs/jquerybookmarks/__init__.py
vs/jquerybookmarks/configure.zcml
vs/jquerybookmarks/header.txt
vs/jquerybookmarks/profiles.zcml
vs/jquerybookmarks/setuphandlers.py
vs/jquerybookmarks/tests.py
vs/jquerybookmarks/version.txt
vs/jquerybookmarks/browser/__init__.py
vs/jquerybookmarks/browser/configure.zcml
vs/jquerybookmarks/browser/interfaces.py
vs/jquerybookmarks/browser/viewlet.pt
vs/jquerybookmarks/browser/viewlets.py
vs/jquerybookmarks/browser/images/README.txt
vs/jquerybookmarks/browser/images/bookmarks.png
vs/jquerybookmarks/browser/javascript/jquery.bookmark.ext.min.js
vs/jquerybookmarks/browser/javascript/jquery.bookmark.min.js
vs/jquerybookmarks/browser/stylesheets/README.txt
vs/jquerybookmarks/browser/stylesheets/jquery.bookmark.css
vs/jquerybookmarks/browser/stylesheets/main.css
vs/jquerybookmarks/profiles/default/cssregistry.xml
vs/jquerybookmarks/profiles/default/jsregistry.xml
vs/jquerybookmarks/profiles/default/metadata.xml
vs/jquerybookmarks/profiles/default/viewlets.xml
vs/jquerybookmarks/profiles/default/vs.jquerybookmarks_various.txt