Metadata-Version: 1.0
Name: vs.jquerybookmarks
Version: 0.1.5
Summary: jquery.bookmark integration with Plone 4
Home-page: http://pypi.python.org/pypi/vs.jquerybookmarks
Author: Andreas Jung
Author-email: infp@zopyx.com
License: GPL
Platform: UNKNOWN
Classifier: Framework :: Plone
Classifier: Framework :: Plone :: 4.0
Classifier: Framework :: Plone :: 4.1
Classifier: Framework :: Plone :: 4.2
Classifier: Programming Language :: Python
